realitydefender/__init__.py
realitydefender/client/__init__.py
realitydefender/client/http_client.py
realitydefender/core/constants.py
realitydefender/core/events.py
realitydefender/detection/__init__.py
realitydefender/detection/results.py
realitydefender/detection/upload.py
realitydefender/errors.py
realitydefender/model.py
realitydefender/py.typed
realitydefender/reality_defender.py
realitydefender/utils/__init__.py
realitydefender/utils/async_utils.py
realitydefender/utils/file_utils.py
realitydefender-0.1.9.dist-info/WHEEL
realitydefender-0.1.9.dist-info/METADATA
realitydefender-0.1.9.dist-info/RECORD
