Metadata-Version: 2.4
Name: realitydefender
Version: 0.1.9
Summary: SDK for the Reality Defender deepfake detection API
Keywords: deepfake,ai,detection,reality defender,media authentication,computer vision
Author: Reality Defender
Author-email: Reality Defender <support@realitydefender.com>
License-Expression: Apache-2.0
Classifier: Development Status :: 4 - Beta
Classifier: Intended Audience :: Developers
Classifier: Programming Language :: Python :: 3
Classifier: Programming Language :: Python :: 3.10
Classifier: Programming Language :: Python :: 3.11
Classifier: Programming Language :: Python :: 3.12
Classifier: Programming Language :: Python :: 3.13
Classifier: Topic :: Software Development :: Libraries :: Python Modules
Classifier: Topic :: Multimedia :: Graphics
Classifier: Topic :: Scientific/Engineering :: Artificial Intelligence
Classifier: Topic :: Security
Requires-Dist: aiohttp>=3.8.0
Requires-Dist: asyncio-atexit>=1.0.1
Requires-Dist: certifi>=2025.4.26
Requires-Python: >=3.10
Project-URL: Documentation, https://github.com/Reality-Defender/eng-sdk/tree/main/python
Project-URL: Issue Tracker, https://github.com/Reality-Defender/eng-sdk/issues
Project-URL: Source, https://github.com/Reality-Defender/eng-sdk
